pypletics/__init__.py
pypletics/introduction.py
pypletics/network.py
pypletics/structured.py
pypletics-0.0.4.8.dist-info/DESCRIPTION.rst
pypletics-0.0.4.8.dist-info/METADATA
pypletics-0.0.4.8.dist-info/RECORD
pypletics-0.0.4.8.dist-info/WHEEL
pypletics-0.0.4.8.dist-info/entry_points.txt
pypletics-0.0.4.8.dist-info/metadata.json
pypletics-0.0.4.8.dist-info/top_level.txt
